greaterprompt/__init__.py
greaterprompt/cli.py
greaterprompt/optimizer.py
greaterprompt/core/__init__.py
greaterprompt/core/TextGrad/README.md
greaterprompt/core/TextGrad/__init__.py
greaterprompt/core/TextGrad/.idea/.gitignore
greaterprompt/core/TextGrad/.idea/PO_Baseline.iml
greaterprompt/core/TextGrad/.idea/deployment.xml
greaterprompt/core/TextGrad/.idea/misc.xml
greaterprompt/core/TextGrad/.idea/modules.xml
greaterprompt/core/TextGrad/.idea/vcs.xml
greaterprompt/core/TextGrad/.idea/inspectionProfiles/profiles_settings.xml
greaterprompt/core/TextGrad/textgrad_ollm/.gitignore
greaterprompt/core/TextGrad/textgrad_ollm/LICENSE
greaterprompt/core/TextGrad/textgrad_ollm/MANIFEST.in
greaterprompt/core/TextGrad/textgrad_ollm/README.md
greaterprompt/core/TextGrad/textgrad_ollm/setup.py
greaterprompt/core/TextGrad/textgrad_ollm/assets/analogy.png
greaterprompt/core/TextGrad/textgrad_ollm/assets/logo_full.png
greaterprompt/core/TextGrad/textgrad_ollm/evaluation/prompt_optimization.py
greaterprompt/core/TextGrad/textgrad_ollm/evaluation/solution_optimization.py
greaterprompt/core/TextGrad/textgrad_ollm/evaluation/solution_optimization_mm.py
greaterprompt/core/TextGrad/textgrad_ollm/evaluation/code_optimization/README.md
greaterprompt/core/TextGrad/textgrad_ollm/evaluation/code_optimization/__init__.py
greaterprompt/core/TextGrad/textgrad_ollm/evaluation/code_optimization/leetcode_testtime_with_supervision.py
greaterprompt/core/TextGrad/textgrad_ollm/evaluation/code_optimization/prompts.py
greaterprompt/core/TextGrad/textgrad_ollm/evaluation/code_optimization/evaluators/__init__.py
greaterprompt/core/TextGrad/textgrad_ollm/evaluation/code_optimization/evaluators/lt_eval.py
greaterprompt/core/TextGrad/textgrad_ollm/evaluation/code_optimization/evaluators/py_eval.py
greaterprompt/core/TextGrad/textgrad_ollm/evaluation/code_optimization/evaluators/utils.py
greaterprompt-1.1.4.dist-info/METADATA
greaterprompt-1.1.4.dist-info/WHEEL
greaterprompt-1.1.4.dist-info/licenses/LICENSE
greaterprompt-1.1.4.dist-info/RECORD
