Metadata-Version: 2.4
Name: greaterprompt
Version: 1.1.4
Summary: A Unified, Customizable, and High-Performing Open-Source Toolkit for Prompt Optimization
Project-URL: Homepage, https://github.com/WenliangZhoushan/GreaterPrompt
Author-email: Wenliang Zheng <wenliangz2004@gmail.com>, Sarkar Snigdha Sarathi Das <sfd5525@psu.edu>, Rui Zhang <rmz5227@psu.edu>
Maintainer-email: Wenliang Zheng <wenliangz2004@gmail.com>
License-Expression: MIT
License-File: LICENSE
Classifier: Development Status :: 3 - Alpha
Classifier: Intended Audience :: Developers
Classifier: Intended Audience :: Science/Research
Classifier: Programming Language :: Python :: 3
Classifier: Topic :: Scientific/Engineering :: Artificial Intelligence
Requires-Dist: accelerate
Requires-Dist: altair
Requires-Dist: autopep8==2.3.2
Requires-Dist: black==25.1.0
Requires-Dist: datasets==3.3.2
Requires-Dist: diskcache==5.6.3
Requires-Dist: fschat
Requires-Dist: graphviz==0.20.3
Requires-Dist: guidance==0.0.64
Requires-Dist: httpx==0.28.1
Requires-Dist: numpy
Requires-Dist: openai==0.27.8
Requires-Dist: pandas==2.2.3
Requires-Dist: pillow==11.1.0
Requires-Dist: platformdirs==4.3.6
Requires-Dist: protobuf==5.29.4
Requires-Dist: psutil
Requires-Dist: pytest==8.3.5
Requires-Dist: python-dotenv==1.0.1
Requires-Dist: python-levenshtein==0.27.1
Requires-Dist: requests==2.32.3
Requires-Dist: retrying==1.3.4
Requires-Dist: setuptools==75.8.0
Requires-Dist: streamlit==1.43.0
Requires-Dist: tenacity==9.0.0
Requires-Dist: torch==2.3.1
Requires-Dist: tqdm==4.67.1
Requires-Dist: transformers==4.48.3
Requires-Dist: vllm==0.5.3.post1
